MANIFEST.in
README.md
requirements.txt
setup.py
transit_utils/__init__.py
transit_utils/transit_utils.py
transit_utils.egg-info/PKG-INFO
transit_utils.egg-info/SOURCES.txt
transit_utils.egg-info/dependency_links.txt
transit_utils.egg-info/requires.txt
transit_utils.egg-info/top_level.txt