Metadata-Version: 1.1
Name: transit-utils
Version: 0.36
Summary: A small collection of methods for analyzing transit data
Home-page: https://github.com/BoiseStatePlanetary/transit_utils
Author: Brian Jackson
Author-email: bjackson@boisestate.edu
License: BSD
Download-URL: https://github.com/BoiseStatePlanetary/transit_utils/archive/0.36.tar.gz
Platform: UNKNOWN
Classifier: Development Status :: 3 - Alpha
Classifier: Intended Audience :: Developers
Classifier: Programming Language :: Python :: 3
